flask_of_oil/__init__.py
flask_of_oil/jwt_validator.py
flask_of_oil/oauth_filter.py
flask_of_oil/opaque_validator.py
flask_of_oil/tools.py
Flask_of_Oil-1.2.0.dist-info/LICENSE.txt
Flask_of_Oil-1.2.0.dist-info/METADATA
Flask_of_Oil-1.2.0.dist-info/WHEEL
Flask_of_Oil-1.2.0.dist-info/top_level.txt
Flask_of_Oil-1.2.0.dist-info/RECORD
