Metadata-Version: 2.1
Name: Flask-of-Oil
Version: 1.2.0
Summary: Flask OAuth Filter - an OAuth Interceptor Logic
Home-page: https://github.com/curity/flask-of-oil
Author: Curity AB
Author-email: info@curity.io
License: Apache Software License
Keywords: oauth,flask,introspection,access token,jwt,opaque
Classifier: Development Status :: 5 - Production/Stable
Classifier: Framework :: Flask
Classifier: Intended Audience :: Developers
Classifier: Topic :: Software Development :: Libraries :: Python Modules
Classifier: License :: OSI Approved :: Apache Software License
Classifier: Programming Language :: Python :: 3
Classifier: Topic :: Security
License-File: LICENSE.txt
Requires-Dist: requests
Requires-Dist: cachelib
Requires-Dist: Flask
Requires-Dist: pyjwkest
